{
    "keep": {
        "days": true,
        "amount": 14
    },
    "auditLog": "logs\\requests\\daily\\.66602cdde70fd43456e51d0c9addc83824638c4d-audit.json",
    "files": [
        {
            "date": 1645587205644,
            "name": "logs\\requests\\daily\\2022-02-23.log",
            "hash": "53d04f2354880991412ed9d413c68ade"
        },
        {
            "date": 1645671185389,
            "name": "logs\\requests\\daily\\2022-02-24.log",
            "hash": "1def0095929de4ba42f3e680de61d390"
        },
        {
            "date": 1645761080581,
            "name": "logs\\requests\\daily\\2022-02-25.log",
            "hash": "4e2d08e3a72684295c197717dcc794d0"
        },
        {
            "date": 1645887665513,
            "name": "logs\\requests\\daily\\2022-02-26.log",
            "hash": "f05b96dd8ccbc980481c0b29abf9de2a"
        },
        {
            "date": 1646016513392,
            "name": "logs\\requests\\daily\\2022-02-28.log",
            "hash": "3124ec0731912cd31a43113e63d3874e"
        },
        {
            "date": 1646119950352,
            "name": "logs\\requests\\daily\\2022-03-01.log",
            "hash": "e199df7b4ce73b8a7d071046229dfd30"
        },
        {
            "date": 1646189308001,
            "name": "logs\\requests\\daily\\2022-03-02.log",
            "hash": "f6b1e02340f82e2ceb2f87a6ee559cd6"
        },
        {
            "date": 1646274768585,
            "name": "logs\\requests\\daily\\2022-03-03.log",
            "hash": "5e9e7584c64ee70007ef523a4f4c0bfb"
        },
        {
            "date": 1646361583689,
            "name": "logs\\requests\\daily\\2022-03-04.log",
            "hash": "b7fbf12bcf79105720cdee8143cb050d"
        },
        {
            "date": 1646634298270,
            "name": "logs\\requests\\daily\\2022-03-07.log",
            "hash": "dfd1ca42991c09b3ff405db85f83e302"
        },
        {
            "date": 1646706817938,
            "name": "logs\\requests\\daily\\2022-03-08.log",
            "hash": "44c2d1c80552ca92e0038873a604e193"
        },
        {
            "date": 1646793676067,
            "name": "logs\\requests\\daily\\2022-03-09.log",
            "hash": "3d8c165540e99a8836f93517950fbe2b"
        }
    ],
    "hashType": "md5"
}